pp/__init__.py
pp/server/__init__.py
pp/server/cli.py
pp/server/config.toml
pp/server/converters.py
pp/server/logger.py
pp/server/main.py
pp/server/registry.py
pp/server/server.py
pp/server/templates.py
pp/server/util.py
pp/server/_templates/__init__.py
pp/server/_templates/circusd.ini
pp/server/_templates/server.ini
pp/server/scripts/rasterize.js
pp/server/static/default.css
pp/server/static/pp-logo.png
pp/server/static/zopyx_logo.png
pp/server/templates/index.html
pp/server/test_data/__init__.py
pp/server/test_data/html/default.css
pp/server/test_data/html/index.html
pp/server/test_data/speedata/data.xml
pp/server/test_data/speedata/index.html
pp/server/test_data/speedata/layout.xml
pp/server/tests/__init__.py
pp/server/tests/index.html
pp/server/tests/test_api.py
pp/server/tests/test_utils.py
pp_server-3.5.6.dist-info/licenses/LICENSE.txt
pp_server-3.5.6.dist-info/METADATA
pp_server-3.5.6.dist-info/WHEEL
pp_server-3.5.6.dist-info/entry_points.txt
pp_server-3.5.6.dist-info/top_level.txt
pp_server-3.5.6.dist-info/RECORD
