Metadata-Version: 2.4
Name: pp.server
Version: 3.5.6
Summary: pp.server - Produce & Publish Server
Author-email: Andreas Jung <info@zopyx.com>
Project-URL: Homepage, http://pypi.python.org/pypi/pp.server
Keywords: web,fastapi,pdf,unoconv,conversion,princexml,pdfreactor
Classifier: Programming Language :: Python
Classifier: Programming Language :: Python :: 3.12
Classifier: Programming Language :: Python :: 3.13
Classifier: Framework :: FastAPI
Classifier: Topic :: Internet :: WWW/HTTP
Requires-Python: >=3.12
License-File: LICENSE.txt
Requires-Dist: aiofiles>=24.1.0
Requires-Dist: click>=8.1.7
Requires-Dist: easyprocess>=1.1
Requires-Dist: fastapi>=0.115.6
Requires-Dist: httptools>=0.6.4
Requires-Dist: hypercorn>=0.17.3
Requires-Dist: uvicorn>=0.20.0
Requires-Dist: jinja2>=3.1.4
Requires-Dist: loguru>=0.7.2
Requires-Dist: plac>=1.4.3
Requires-Dist: python-multipart>=0.0.19
Requires-Dist: webtest>=3.0.2
Requires-Dist: tomli>=2.0.0; python_version < "3.11"
Provides-Extra: testing
Requires-Dist: pytest>=8.0.0; extra == "testing"
Requires-Dist: pytest-asyncio>=0.23.0; extra == "testing"
Requires-Dist: pytest-cov>=4.0.0; extra == "testing"
Provides-Extra: dev
Requires-Dist: ruff>=0.1.0; extra == "dev"
Requires-Dist: mypy>=1.7.0; extra == "dev"
Requires-Dist: twine>=4.0.0; extra == "dev"
Requires-Dist: build>=1.0.0; extra == "dev"
Requires-Dist: pytest>=8.0.0; extra == "dev"
Requires-Dist: pytest-asyncio>=0.23.0; extra == "dev"
Requires-Dist: pytest-cov>=4.0.0; extra == "dev"
Requires-Dist: httpx>=0.24.0; extra == "dev"
Dynamic: license-file
